setup.py
ckanext/__init__.py
ckanext/htsql/__init__.py
ckanext/htsql/plugin.py
ckanext/htsql/logic/__init__.py
ckanext/htsql/logic/action.py
ckanext_htsql.egg-info/PKG-INFO
ckanext_htsql.egg-info/SOURCES.txt
ckanext_htsql.egg-info/dependency_links.txt
ckanext_htsql.egg-info/entry_points.txt
ckanext_htsql.egg-info/namespace_packages.txt
ckanext_htsql.egg-info/not-zip-safe
ckanext_htsql.egg-info/requires.txt
ckanext_htsql.egg-info/top_level.txt