Metadata-Version: 1.0
Name: ckanext-htsql
Version: 0.1.1
Summary: Enables HTSQL queries in the new datastore in CKAN.
Home-page: UNKNOWN
Author: Dominik Moritz
Author-email: UNKNOWN
License: AGPL
Keywords: ckan,datastore,htsql
Platform: UNKNOWN
